LICENSE
README.md
pyproject.toml
ch_filing/__init__.py
ch_filing/__main__.py
ch_filing/client.py
ch_filing/company_data.py
ch_filing/envelope.py
ch_filing/form_submission.py
ch_filing/state.py
ch_filing/submission_status.py
ch_filing/test_server/__init__.py
ch_filing/test_server/__main__.py
ch_filing/test_server/data.py
ch_filing/test_server/handlers.py
ch_filing/test_server/responses.py
ch_filing/test_server/server.py
companies_house_filing.egg-info/PKG-INFO
companies_house_filing.egg-info/SOURCES.txt
companies_house_filing.egg-info/dependency_links.txt
companies_house_filing.egg-info/entry_points.txt
companies_house_filing.egg-info/requires.txt
companies_house_filing.egg-info/top_level.txt