Metadata-Version: 2.4
Name: companies-house-filing
Version: 0.3.0
Summary: UK Companies House accounts filing for GnuCash users
Author-email: Cybermaggedon <mark@cyberapocalypse.co.uk>
License: GPL-3.0-or-later
Project-URL: Homepage, https://github.com/cybermaggedon/gnucash-ch-filing
Project-URL: Repository, https://github.com/cybermaggedon/gnucash-ch-filing
Project-URL: Download, https://github.com/cybermaggedon/gnucash-uk-corptax/archive/refs/tags/v0.2.1.tar.gz
Classifier: Programming Language :: Python :: 3
Classifier: License :: OSI Approved :: GNU General Public License v3 or later (GPLv3+)
Classifier: Operating System :: OS Independent
Requires-Python: >=3.6
License-File: LICENSE
Requires-Dist: lxml
Requires-Dist: requests
Provides-Extra: test
Requires-Dist: pytest>=7.0; extra == "test"
Requires-Dist: pytest-cov>=4.0; extra == "test"
Requires-Dist: pytest-mock>=3.0; extra == "test"
Requires-Dist: pytest-asyncio>=0.21.0; extra == "test"
Provides-Extra: dev
Requires-Dist: pytest>=7.0; extra == "dev"
Requires-Dist: pytest-cov>=4.0; extra == "dev"
Requires-Dist: pytest-mock>=3.0; extra == "dev"
Requires-Dist: pytest-asyncio>=0.21.0; extra == "dev"
Requires-Dist: black>=23.0.0; extra == "dev"
Requires-Dist: isort>=5.12.0; extra == "dev"
Requires-Dist: flake8>=6.0.0; extra == "dev"
Requires-Dist: mypy>=1.0.0; extra == "dev"
Requires-Dist: bandit>=1.7.0; extra == "dev"
Dynamic: license-file
